Metadata-Version: 2.1
Name: minerva-python
Version: 0.1.0.dev0
Summary: Minerva access from within python
Home-page: https://gitlab.mpcdf.mpg.de/dboe/minerva_py
Author: Daniel Böckenhoff
Author-email: dboe@ipp.mpg.de
License: MIT License
Project-URL: Documentation, https://gitlab.mpcdf.mpg.de/dboe/minerva_py
Project-URL: Source, https://gitlab.mpcdf.mpg.de/dboe/minerva_py
Keywords: py4j,gateway,python-java-bridge
Platform: UNKNOWN
Classifier: Development Status :: 3 - Alpha
Classifier: License :: OSI Approved :: MIT License
Classifier: Programming Language :: Python
Classifier: Programming Language :: Python :: 2.7
Classifier: Programming Language :: Python :: 3
Classifier: Programming Language :: Python :: 3.2
Classifier: Programming Language :: Python :: 3.3
Classifier: Programming Language :: Python :: 3.4
Classifier: Programming Language :: Python :: 3.5
Classifier: Programming Language :: Python :: 3.6
Classifier: Programming Language :: Python :: 3.7
Classifier: Programming Language :: Python :: 3.8
